pycorrcat/__init__.py
pycorrcat/pycorrcat.py
test/__init__.py
test/test_pycorrcat.py
pycorr-0.1.5.dist-info/LICENSE
pycorr-0.1.5.dist-info/METADATA
pycorr-0.1.5.dist-info/WHEEL
pycorr-0.1.5.dist-info/top_level.txt
pycorr-0.1.5.dist-info/RECORD
