Metadata-Version: 2.1
Name: pycorr
Version: 0.1.5
Summary: Python package for calculating correlation amongst categorical variables
Home-page: https://github.com/MavericksDS/pycorr
Author: Anurag Kumar Mishra
Author-email: anuragkm25@outlook.com
License: UNKNOWN
Platform: UNKNOWN
Classifier: Programming Language :: Python :: 3.7
Classifier: License :: OSI Approved :: GNU General Public License v3 (GPLv3)
